alectio_sdk/__init__.py
alectio_sdk/metrics/__init__.py
alectio_sdk/metrics/classification/__init__.py
alectio_sdk/metrics/classification/classification.py
alectio_sdk/metrics/multilabel_classification/__init__.py
alectio_sdk/metrics/multilabel_classification/multilabel_classification.py
alectio_sdk/metrics/object_detection/CM.py
alectio_sdk/metrics/object_detection/__init__.py
alectio_sdk/metrics/object_detection/_object_detection.py
alectio_sdk/metrics/object_detection/imports.py
alectio_sdk/metrics/object_detection/utils.py
alectio_sdk/metrics/object_segmentation/SegCM.py
alectio_sdk/metrics/object_segmentation/__init__.py
alectio_sdk/metrics/object_segmentation/_object_segmentation.py
alectio_sdk/metrics/object_segmentation/rangeutils.py
alectio_sdk/metrics/regression/__init__.py
alectio_sdk/metrics/regression/regression.py
alectio_sdk/metrics/timeseries/__init__.py
alectio_sdk/metrics/timeseries/timeseries.py
alectio_sdk/sdk/__init__.py
alectio_sdk/sdk/alectio_dataset.py
alectio_sdk/sdk/api_client.py
alectio_sdk/sdk/bayesian_inference.py
alectio_sdk/sdk/config.json
alectio_sdk/sdk/console.py
alectio_sdk/sdk/data_initialisation.py
alectio_sdk/sdk/data_streaming.py
alectio_sdk/sdk/gcp_storage.py
alectio_sdk/sdk/multiple_seed_pool.py
alectio_sdk/sdk/pipeline.py
alectio_sdk/sdk/sql_client.py
alectio_sdk/sdk/utils.py
alectio_sdk/tensorflow_utils/__init__.py
alectio_sdk/tensorflow_utils/utils/__init__.py
alectio_sdk/tensorflow_utils/utils/boxutils.py
alectio_sdk/tensorflow_utils/utils/tfdeterministic.py
alectio_sdk/torch_utils/__init__.py
alectio_sdk/torch_utils/utils/__init__.py
alectio_sdk/torch_utils/utils/boxutils.py
alectio_sdk/torch_utils/utils/pytorchdeterministic.py
alectio_sdk-1.0.35.dist-info/METADATA
alectio_sdk-1.0.35.dist-info/WHEEL
alectio_sdk-1.0.35.dist-info/entry_points.txt
alectio_sdk-1.0.35.dist-info/top_level.txt
alectio_sdk-1.0.35.dist-info/RECORD
