Metadata-Version: 2.1
Name: alectio_sdk
Version: 1.0.35
Summary: Integrate customer side ML application with the Alectio Platform
Home-page: https://github.com/alectio/SDK
Author: Alectio
Author-email: admin@alectio.com
Classifier: Programming Language :: Python :: 3
Classifier: Intended Audience :: Developers
Classifier: Intended Audience :: Science/Research
Classifier: License :: OSI Approved :: MIT License
Classifier: Topic :: Scientific/Engineering :: Artificial Intelligence
Classifier: Topic :: Software Development :: Libraries :: Python Modules
Classifier: Topic :: System :: Logging
Classifier: Topic :: System :: Monitoring
Requires-Python: >=3.6
Requires-Dist: python-dateutil >=2.8.1
Requires-Dist: urllib3 >=1.25.9
Requires-Dist: scikit-learn
Requires-Dist: wheel
Requires-Dist: pickle-mixin
Requires-Dist: opencv-python-headless
Requires-Dist: rich
Requires-Dist: typer
Requires-Dist: pandas
Requires-Dist: google-cloud-storage
Requires-Dist: google-auth
Requires-Dist: scikit-build
Requires-Dist: codecarbon
Requires-Dist: crcmod
Requires-Dist: google-cloud-kms
Requires-Dist: tensorflow-probability
